[
  {
    "id": "33655e53-46cb-483f-bf7f-a3842869e65d",
    "name": "Naomi Hettinger",
    "number": "3561863892088549",
    "valid_thru": "07/25",
    "cvv": "195",
    "type": "visa",
    "card_details": {
      "current_limit": 47965,
      "online_transactions": false,
      "atm_withdrawals": false,
      "atm_limit": 9945
    },
    "transactions": [
      {
        "id": "9dbbb91d-61d9-4516-9f30-01942c4e51a6",
        "vendor": "Minima Tricesimus Feil",
        "vendor_type": "flights",
        "date": "9/1/2023",
        "amount": "232",
        "type": "credit"
      },
      {
        "id": "87d0503a-5c93-4895-b013-372583936fff",
        "vendor": "Sulum LLC",
        "vendor_type": "accessories",
        "date": "3/19/2024",
        "amount": "782",
        "type": "credit"
      },
      {
        "id": "baa3995e-cec9-42a9-a96c-cf4a95e4c8f6",
        "vendor": "Torqueo Admiratio Kreiger",
        "vendor_type": "flights",
        "date": "3/29/2024",
        "amount": "227",
        "type": "credit"
      },
      {
        "id": "9caa1914-9c9b-4397-9382-da435071b58a",
        "vendor": "Numquam Compono Rempel",
        "vendor_type": "flights",
        "date": "6/2/2023",
        "amount": "168",
        "type": "debit"
      },
      {
        "id": "84e1da8f-c3b8-4556-9a0e-12d985955bc5",
        "vendor": "Timor Sons",
        "vendor_type": "flights",
        "date": "2/11/2024",
        "amount": "24",
        "type": "debit"
      },
      {
        "id": "39df7120-4ac5-4697-9441-e2608aa680c4",
        "vendor": "Tenetur Stark",
        "vendor_type": "subscriptions",
        "date": "4/15/2024",
        "amount": "638",
        "type": "debit"
      },
      {
        "id": "7d6d5731-b9de-4774-946e-9f791aff3e3c",
        "vendor": "Viduo Velit LLC",
        "vendor_type": "accessories",
        "date": "5/4/2024",
        "amount": "147",
        "type": "debit"
      },
      {
        "id": "d838d568-134d-404f-9eba-56fe478d60cc",
        "vendor": "Speculum Curriculum LLC",
        "vendor_type": "subscriptions",
        "date": "1/28/2024",
        "amount": "307",
        "type": "debit"
      }
    ]
  },
  {
    "id": "712a03ab-8857-4208-85a7-6bb51ffa8488",
    "name": "Veronica Leuschke",
    "number": "5018079390628223",
    "valid_thru": "06/29",
    "cvv": "954",
    "type": "amex",
    "card_details": {
      "current_limit": 11830,
      "online_transactions": true,
      "atm_withdrawals": true,
      "atm_limit": 16432
    },
    "transactions": [
      {
        "id": "8dd6116d-d91a-4707-b179-6363c84df2a0",
        "vendor": "Cupiditas Deprecator Jacobs",
        "vendor_type": "flights",
        "date": "6/13/2023",
        "amount": "708",
        "type": "debit"
      },
      {
        "id": "e61a78e7-7ff5-47d2-88d1-21d7ce28336b",
        "vendor": "Decor Purdy",
        "vendor_type": "flights",
        "date": "5/6/2024",
        "amount": "391",
        "type": "credit"
      },
      {
        "id": "a71c1904-f5f6-4d5d-8239-c1ee79ad02e8",
        "vendor": "Abduco Sons",
        "vendor_type": "accessories",
        "date": "5/25/2024",
        "amount": "48",
        "type": "debit"
      },
      {
        "id": "3926be9a-b9a5-45d1-8018-494577d0f4c6",
        "vendor": "Templum Substantia Maggio",
        "vendor_type": "flights",
        "date": "4/5/2024",
        "amount": "381",
        "type": "debit"
      },
      {
        "id": "69c902e1-c6bf-44a0-83b4-ea4ec5cbee52",
        "vendor": "Curtus LLC",
        "vendor_type": "flights",
        "date": "7/1/2023",
        "amount": "450",
        "type": "credit"
      },
      {
        "id": "da65d1b1-6e80-4fd4-94b7-f51551886db0",
        "vendor": "Asper Heidenreich",
        "vendor_type": "accessories",
        "date": "1/5/2024",
        "amount": "321",
        "type": "credit"
      },
      {
        "id": "fc4e4aa2-556b-441c-b5a3-02ff38995868",
        "vendor": "Subnecto O'Reilly",
        "vendor_type": "subscriptions",
        "date": "2/20/2024",
        "amount": "712",
        "type": "credit"
      },
      {
        "id": "0b90c32f-0556-458f-a731-95970a4cb4d0",
        "vendor": "Altus Leannon",
        "vendor_type": "accessories",
        "date": "9/6/2023",
        "amount": "190",
        "type": "credit"
      }
    ]
  },
  {
    "id": "b8a2f376-f527-451b-be74-16afd992eee5",
    "name": "Mike Harris I",
    "number": "3540206408442147",
    "valid_thru": "10/33",
    "cvv": "198",
    "type": "mastercard",
    "card_details": {
      "current_limit": 75705,
      "online_transactions": false,
      "atm_withdrawals": false,
      "atm_limit": 12343
    },
    "transactions": [
      {
        "id": "48c9e4c2-4818-48ec-9daa-dd2ca991fcc7",
        "vendor": "Defendo Cibo Funk",
        "vendor_type": "accessories",
        "date": "10/7/2023",
        "amount": "375",
        "type": "credit"
      },
      {
        "id": "84828969-0861-4dad-8625-6dd45c4bb635",
        "vendor": "Villa Alienus Tremblay",
        "vendor_type": "subscriptions",
        "date": "7/20/2023",
        "amount": "83",
        "type": "debit"
      },
      {
        "id": "254ae065-b07f-44a1-bd15-a877b800c8fa",
        "vendor": "Autem Group",
        "vendor_type": "subscriptions",
        "date": "7/9/2023",
        "amount": "339",
        "type": "credit"
      },
      {
        "id": "576463ba-5ec8-472d-a05a-61097b7d4985",
        "vendor": "Patruus Adipiscor Schneider",
        "vendor_type": "subscriptions",
        "date": "5/11/2024",
        "amount": "404",
        "type": "debit"
      },
      {
        "id": "64639f88-2230-4926-b730-8d79e4acf52f",
        "vendor": "Caveo Fadel",
        "vendor_type": "flights",
        "date": "8/3/2023",
        "amount": "168",
        "type": "credit"
      },
      {
        "id": "c190bc5a-2ec6-4f34-be9f-4ebeab0b0003",
        "vendor": "Clarus Group",
        "vendor_type": "flights",
        "date": "1/28/2024",
        "amount": "345",
        "type": "debit"
      },
      {
        "id": "4e564aa8-5a77-4785-823a-6d13ae936a24",
        "vendor": "Cetera Cetera LLC",
        "vendor_type": "subscriptions",
        "date": "3/3/2024",
        "amount": "433",
        "type": "debit"
      },
      {
        "id": "ed2ca520-b744-4ed7-974c-e17c4330279e",
        "vendor": "Carbo Adamo Schulist",
        "vendor_type": "subscriptions",
        "date": "12/28/2023",
        "amount": "556",
        "type": "credit"
      }
    ]
  },
  {
    "id": "502b5763-6167-436a-b5c4-6188621f7fa8",
    "name": "Terrell Schmitt",
    "number": "5219761345998234",
    "valid_thru": "12/27",
    "cvv": "748",
    "type": "visa",
    "card_details": {
      "current_limit": 5339,
      "online_transactions": true,
      "atm_withdrawals": true,
      "atm_limit": 6069
    },
    "transactions": [
      {
        "id": "99f2a35a-4d52-4995-8049-60acab1807f2",
        "vendor": "Thesaurus Claudeo Halvorson",
        "vendor_type": "subscriptions",
        "date": "8/5/2023",
        "amount": "790",
        "type": "credit"
      },
      {
        "id": "8a9ebf28-55f2-475e-8560-92c260e0e7cd",
        "vendor": "Ad Abscido Sons",
        "vendor_type": "flights",
        "date": "9/30/2023",
        "amount": "351",
        "type": "debit"
      },
      {
        "id": "ac874bc0-c88a-433a-991a-be5b20ba6a41",
        "vendor": "Vitae Tantillus Kilback",
        "vendor_type": "subscriptions",
        "date": "3/13/2024",
        "amount": "327",
        "type": "credit"
      },
      {
        "id": "955eecb2-0b61-42eb-a717-09e642eb61f4",
        "vendor": "Ventito Victoria Jacobson",
        "vendor_type": "accessories",
        "date": "8/2/2023",
        "amount": "153",
        "type": "debit"
      },
      {
        "id": "4a02e485-ba18-453e-b35d-995d327543d9",
        "vendor": "Soleo Kuhlman",
        "vendor_type": "flights",
        "date": "4/1/2024",
        "amount": "704",
        "type": "credit"
      },
      {
        "id": "16b15cd0-583c-439e-9bad-19ab8ef99587",
        "vendor": "Speciosus Cruentus Hyatt",
        "vendor_type": "subscriptions",
        "date": "8/27/2023",
        "amount": "157",
        "type": "credit"
      },
      {
        "id": "27e2fd28-f1b6-4c67-bbc6-d7cca6aa3823",
        "vendor": "Velum Lowe",
        "vendor_type": "accessories",
        "date": "1/8/2024",
        "amount": "603",
        "type": "credit"
      },
      {
        "id": "499b88db-8344-4ecf-97e8-835ed58d6825",
        "vendor": "Cursim Inc",
        "vendor_type": "accessories",
        "date": "2/22/2024",
        "amount": "180",
        "type": "debit"
      }
    ]
  },
  {
    "id": "62dcca6b-958b-4eb6-bb31-a00d4257fba9",
    "name": "Gwen Walter",
    "number": "36297678756420",
    "valid_thru": "06/26",
    "cvv": "924",
    "type": "amex",
    "card_details": {
      "current_limit": 38296,
      "online_transactions": true,
      "atm_withdrawals": true,
      "atm_limit": 20918
    },
    "transactions": [
      {
        "id": "fc1d5f79-25be-4d1d-89c5-a3417502e3e6",
        "vendor": "Desino Trepide Carter",
        "vendor_type": "subscriptions",
        "date": "10/11/2023",
        "amount": "291",
        "type": "debit"
      },
      {
        "id": "d24516ad-9c23-4404-b290-7c0b6dbd2299",
        "vendor": "Sequi Macejkovic",
        "vendor_type": "flights",
        "date": "3/24/2024",
        "amount": "186",
        "type": "debit"
      },
      {
        "id": "ddb0a469-63c0-450e-ba26-aae72006b650",
        "vendor": "Admoneo Keebler",
        "vendor_type": "flights",
        "date": "10/3/2023",
        "amount": "523",
        "type": "debit"
      },
      {
        "id": "bd29eb9b-947f-4718-a562-4d94969d076e",
        "vendor": "Cena Weimann",
        "vendor_type": "accessories",
        "date": "3/26/2024",
        "amount": "148",
        "type": "credit"
      },
      {
        "id": "5a9daaac-7f18-4c40-822f-77d02897cdd6",
        "vendor": "Sursum Valde Huel",
        "vendor_type": "flights",
        "date": "1/18/2024",
        "amount": "792",
        "type": "credit"
      },
      {
        "id": "f04598dc-82b1-4d97-a79f-a5944b515236",
        "vendor": "Deinde Renner",
        "vendor_type": "flights",
        "date": "4/1/2024",
        "amount": "403",
        "type": "debit"
      },
      {
        "id": "04522b13-4230-450e-970b-bc0ee5e35e12",
        "vendor": "Suppono Heidenreich",
        "vendor_type": "subscriptions",
        "date": "11/29/2023",
        "amount": "281",
        "type": "credit"
      },
      {
        "id": "d9625dcd-dd87-401c-b6bf-b5012ca8cde6",
        "vendor": "Demonstro Clibanus Mitchell",
        "vendor_type": "flights",
        "date": "7/27/2023",
        "amount": "492",
        "type": "debit"
      }
    ]
  }
]
